{
  "id": "software-technology",
  "title": "軟體技術",
  "hideTitle": true,
  "items": [
    {
      "id": "coding-skill",
      "parent": null,
      "t": "程式技能",
      "c": "编程技能",
      "p": "chéng shì jì néng",
      "z": "ㄔㄥˊ ㄕˋ ㄐㄧˋ ㄋㄥˊ",
      "en": "coding skill"
    },
    {
      "id": "Data Structure & Algorithm",
      "parent": "coding-skill",
      "t": "資料結構與演算法",
      "c": "数据结构与算法",
      "p": "zī liào jié gòu yǔ yǎn suàn fǎ",
      "z": "ㄗ ㄌㄧㄠˋ ㄐㄧㄝˊ ㄍㄡˋ ㄩˇ ㄧㄢˇ ㄙㄨㄢˋ ㄈㄚˇ",
      "en": "Data Structure & Algorithm",
      "pointTo": {
        "type": "menupath",
        "data": "github/json",
        "dataLocation": "https://github.com/feelryan/jujuen/blob/Data-Structure-%26-Algorithm/menu-path.json?v=2"
      }
    },
    {
      "id": "certifications",
      "parent": null,
      "t": "IT證照",
      "c": "IT证照",
      "p": "IT zhèng zhào",
      "z": "IT ㄓㄥˋ ㄓㄠˋ",
      "en": "IT certification"
    },
    {
      "id": "google-generative-ai-leader-certification",
      "parent": "certifications",
      "t": "Google Generative AI 領導者認證",
      "c": "Google Generative AI 领导者认证",
      "p": "Google Generative AI lǐng dǎo zhě rèn zhèng",
      "z": "Google Generative AI ㄌㄧㄥˇ ㄉㄠˇ ㄓㄜˇ ㄖㄣˋ ㄓㄥˋ",
      "en": "Google Generative AI Leader Certification",
      "pointTo": {
        "type": "menupath",
        "data": "github/json",
        "dataLocation": "https://github.com/feelryan/jujuen/blob/google-generative-ai-leader/menu-path.json?v=1"
      }
    },
    {
      "id": "google-professional-cloud-architect-certification",
      "parent": "google-generative-ai-leader-certification",
      "t": "Google 專業雲端架構師認證",
      "c": "Google 专业云端架构师认证",
      "p": "Google zhuān yè yún duān jià gòu shī rèn zhèng",
      "z": "Google ㄓㄨㄢ ㄧㄝˋ ㄩㄣˊ ㄉㄨㄢ ㄐㄧㄚˋ ㄍㄡˋ ㄕ ㄖㄣˋ ㄓㄥˋ",
      "en": "Google Professional Cloud Architect Certification",
      "pointTo": {
        "type": "menupath",
        "data": "github/json",
        "dataLocation": "https://github.com/feelryan/jujuen/blob/google-professional-cloud-architect/menu-path.json?v=1"
      }
    }
  ]
}
