{
    "id": "junior-high",
    "title": "國中科目",
    "items": [
        {
            "id": "taiwan",
            "parent": null,
            "t": "台灣",
            "c": "台湾",
            "p": "tái wān",
            "z": "ㄊㄞˊ ㄨㄢ",
            "en": "Taiwan"
        },
        {
            "id": "math",
            "parent": "taiwan",
            "t": "數學",
            "c": "数学",
            "p": "shù xué",
            "z": "ㄕㄨˋ ㄒㄩㄝˊ",
            "en": "Mathematics",
            "pointTo": {
                "type": "menupath",
                "data": "github/json",
                "dataLocation": "https://github.com/feelryan/jujuen/blob/junior-high/taiwan/math-path.json"
            }
        },
        {
            "id": "nature",
            "parent": "taiwan",
            "t": "自然",
            "c": "自然",
            "p": "zì rán",
            "z": "ㄗˋ ㄖㄢˊ",
            "en": "Nature",
            "pointTo": {
                "type": "menupath",
                "data": "github/json",
                "dataLocation": "https://github.com/feelryan/jujuen/blob/junior-high/taiwan/nature-path.json"
            }
        }
    ]
}